setup.cfg
setup.py
py3weixin/__init__.py
py3weixin/bind.py
py3weixin/client.py
py3weixin/config.py
py3weixin/helper.py
py3weixin/json_import.py
py3weixin/msg_template.py
py3weixin/oauth2.py
py3weixin/reply.py
py3weixin/response.py
py3weixin/lib/Sample.py
py3weixin/lib/WXBizMsgCrypt.py
py3weixin/lib/__init__.py
py3weixin/lib/ierror.py
python3_weixin.egg-info/PKG-INFO
python3_weixin.egg-info/SOURCES.txt
python3_weixin.egg-info/dependency_links.txt
python3_weixin.egg-info/requires.txt
python3_weixin.egg-info/top_level.txt
python3_weixin.egg-info/zip-safe