Metadata-Version: 1.1
Name: python3-weixin
Version: 0.0.9
Summary: Weixin API client for Python 3.x
Home-page: https://github.com/ykbj/python3-weixin
Author: Yang Kai
Author-email: yk1001@live.cn
License: BSD
Download-URL: https://github.com/ykbj/python3-weixin/archive/master.zip
Keywords: python3-weixin,weixin,wechat,sdk
Platform: UNKNOWN
